atomcarla