Metadata-Version: 1.0
Name: atomcarla
Version: 0.3.0
Summary: Python API for communicating with the AtomCarla server.
Home-page: https://atom.auto/
Author: Atom Unreal Engine team
Author-email: yuri.pigo@atom.team
License: MIT License
